setup.py
drf_collection_methods/__init__.py
drf_collection_methods.egg-info/PKG-INFO
drf_collection_methods.egg-info/SOURCES.txt
drf_collection_methods.egg-info/dependency_links.txt
drf_collection_methods.egg-info/requires.txt
drf_collection_methods.egg-info/top_level.txt