Metadata-Version: 1.0
Name: drf-collection-methods
Version: 0.1.0
Summary: Route methods to the base of your collections!
Home-page: https://github.com/gizmag/drf-collection-methods
Author: Gizmag
Author-email: tech@gizmag.com
License: UNKNOWN
Platform: UNKNOWN
